gradle.properties
hexdoc_hexdebug/__gradle_version__.py
hexdoc_hexdebug/__init__.py
hexdoc_hexdebug/__version__.py
hexdoc_hexdebug/_hooks.py
hexdoc_hexdebug/py.typed
hexdoc_hexdebug/recipes.py
hexdoc_hexdebug/_export/.gitignore
hexdoc_hexdebug/_export/__init__.py
hexdoc_hexdebug/_export/generated/__init__.py
hexdoc_hexdebug/_export/generated/hexdebug.hexdoc.json
hexdoc_hexdebug/_export/generated/hexdebug.patterns.hexdoc.json
hexdoc_hexdebug/_export/generated/assets/hexcasting/lang/en_us.flatten.json5
hexdoc_hexdebug/_export/generated/assets/hexcasting/lang/ru_ru.flatten.json5
hexdoc_hexdebug/_export/generated/assets/hexcasting/lang/zh_cn.flatten.json5
hexdoc_hexdebug/_export/generated/assets/hexcasting/patchouli_books/thehexbook/en_us/entries/greatwork/enlightened_splicing_table.json5
hexdoc_hexdebug/_export/generated/assets/hexcasting/patchouli_books/thehexbook/en_us/entries/greatwork/quenching_debuggers.json5
hexdoc_hexdebug/_export/generated/assets/hexcasting/patchouli_books/thehexbook/en_us/entries/items/debugging.json5
hexdoc_hexdebug/_export/generated/assets/hexcasting/patchouli_books/thehexbook/en_us/entries/items/focus_holder.json5
hexdoc_hexdebug/_export/generated/assets/hexcasting/patchouli_books/thehexbook/en_us/entries/items/splicing_table.json5
hexdoc_hexdebug/_export/generated/assets/hexcasting/patchouli_books/thehexbook/en_us/entries/patterns/debugging.json5
hexdoc_hexdebug/_export/generated/assets/hexcasting/patchouli_books/thehexbook/en_us/entries/patterns/enlightened_splicing_table.json5
hexdoc_hexdebug/_export/generated/assets/hexcasting/patchouli_books/thehexbook/en_us/entries/patterns/splicing_table.json5
hexdoc_hexdebug/_export/generated/assets/hexdebug/lang/en_us.flatten.json5
hexdoc_hexdebug/_export/generated/assets/hexdebug/lang/ru_ru.flatten.json5
hexdoc_hexdebug/_export/generated/assets/hexdebug/lang/zh_cn.flatten.json5
hexdoc_hexdebug/_export/generated/assets/hexdebug/models/block/splicing_table.json
hexdoc_hexdebug-0.8.0.1.20.1.1.1.dist-info/METADATA
hexdoc_hexdebug-0.8.0.1.20.1.1.1.dist-info/WHEEL
hexdoc_hexdebug-0.8.0.1.20.1.1.1.dist-info/entry_points.txt
hexdoc_hexdebug-0.8.0.1.20.1.1.1.dist-info/licenses/LICENSE
hexdoc_hexdebug-0.8.0.1.20.1.1.1.dist-info/RECORD
