Metadata-Version: 2.4
Name: hexdoc-hexdebug
Version: 0.8.0.1.20.1.1.1
Summary: Python web book docgen and hexdoc plugin for HexDebug.
Project-URL: Homepage, https://hexdebug.hexxy.media
Project-URL: Source, https://github.com/object-Object/HexDebug
Author: object-Object
License-File: LICENSE
Keywords: hexdoc
Requires-Python: >=3.12
Requires-Dist: hexdoc-hexcasting~=0.11.2.1.0
Requires-Dist: hexdoc-ioticblocks>=1.0.0.1.0
Requires-Dist: hexdoc>=1!0.1.0a34
